README.md
setup.py
PyModelManager.egg-info/PKG-INFO
PyModelManager.egg-info/SOURCES.txt
PyModelManager.egg-info/dependency_links.txt
PyModelManager.egg-info/top_level.txt
modelmanager/__init__.py
modelmanager/feature.py
modelmanager/metric.py
modelmanager/model.py
modelmanager/model_manager.py
modelmanager/model_manager_object.py
modelmanager/project.py
modelmanager/requester.py