Metadata-Version: 2.1
Name: PyModelManager
Version: 0.45.0
Summary: ModelManager API
Home-page: UNKNOWN
Author: Alexander Litvinov
Author-email: alektron@yandex.ru
License: UNKNOWN
Platform: UNKNOWN
Requires-Python: >=3.6
